{
  "project_info": {
    "project_number": "982806935165",
    "project_id": "komsilook",
    "storage_bucket": "komsilook.firebasestorage.app"
  },
  "client": [
    {
      "client_info": {
        "mobilesdk_app_id": "1:982806935165:android:9c9c37ba0db268e6472314",
        "android_client_info": {
          "package_name": "com.icedemon72.komsilook"
        }
      },
      "oauth_client": [],
      "api_key": [
        {
          "current_key": "AIzaSyBmuSe8DAWdYW2fKyE1RvMp1JkcPd7tID4"
        }
      ],
      "services": {
        "appinvite_service": {
          "other_platform_oauth_client": []
        }
      }
    }
  ],
  "configuration_version": "1"
}